experimentation/__init__.py
experimentation/experiment/__init__.py
experimentation/experiment/abstractions/__init__.py
experimentation/experiment/abstractions/experiment_result.py
experimentation/experiment/abstractions/experiment_settings.py
experimentation/experiment/abstractions/experimentation_service.py
experimentation_ChrisPrein-1.0.1.dist-info/LICENSE
experimentation_ChrisPrein-1.0.1.dist-info/METADATA
experimentation_ChrisPrein-1.0.1.dist-info/WHEEL
experimentation_ChrisPrein-1.0.1.dist-info/top_level.txt
experimentation_ChrisPrein-1.0.1.dist-info/RECORD
