Metadata-Version: 2.1
Name: experimentation-ChrisPrein
Version: 1.0.1
Summary: A package for experiment abstractions.
Home-page: https://github.com/ChrisPrein/experimentation
Author: ChrisPrein
Author-email: e01529038@student.tuwien.ac.at
Project-URL: Bug Tracker, https://github.com/ChrisPrein/experimentation/issues
Classifier: Programming Language :: Python :: 3
Classifier: License :: OSI Approved :: MIT License
Classifier: Operating System :: OS Independent
Requires-Python: >=3.6
License-File: LICENSE
